[{
  "_id": {
    "$oid": "68b0981f5955199db1d263ca"
  },
  "message": "Transaction was unsuccessful",
  "type": "warning",
  "createdAt": {
    "$date": "2025-08-28T17:55:43.543Z"
  },
  "updatedAt": {
    "$date": "2025-08-28T17:55:43.543Z"
  },
  "__v": 0
},
{
  "_id": {
    "$oid": "68b09bb95955199db1d26448"
  },
  "message": "Yes, there will be class",
  "type": "info",
  "createdAt": {
    "$date": "2025-08-28T18:11:05.493Z"
  },
  "updatedAt": {
    "$date": "2025-08-28T18:11:05.493Z"
  },
  "__v": 0
},
{
  "_id": {
    "$oid": "68b09bf65955199db1d2644f"
  },
  "message": "Transaction failed. please try again",
  "type": "error",
  "createdAt": {
    "$date": "2025-08-28T18:12:06.710Z"
  },
  "updatedAt": {
    "$date": "2025-08-28T18:12:06.710Z"
  },
  "__v": 0
},
{
  "_id": {
    "$oid": "68b09c2a5955199db1d26452"
  },
  "message": "Transaction successful. Thank you!",
  "type": "success",
  "createdAt": {
    "$date": "2025-08-28T18:12:58.311Z"
  },
  "updatedAt": {
    "$date": "2025-08-28T18:12:58.311Z"
  },
  "__v": 0
},
{
  "_id": {
    "$oid": "68b09c4a5955199db1d26455"
  },
  "message": "Yes, there will be class 12:00pm",
  "type": "info",
  "createdAt": {
    "$date": "2025-08-28T18:13:30.461Z"
  },
  "updatedAt": {
    "$date": "2025-08-28T18:13:30.461Z"
  },
  "__v": 0
},
{
  "_id": {
    "$oid": "68b09f3c5955199db1d26465"
  },
  "message": "Yes, there will be class 12:00pm",
  "type": "info",
  "createdAt": {
    "$date": "2025-08-28T18:26:04.113Z"
  },
  "updatedAt": {
    "$date": "2025-08-28T18:26:04.113Z"
  },
  "__v": 0
},
{
  "_id": {
    "$oid": "68b0a7e25955199db1d2646f"
  },
  "message": "Transaction successful. Thank You!",
  "type": "success",
  "createdAt": {
    "$date": "2025-08-28T19:02:58.915Z"
  },
  "updatedAt": {
    "$date": "2025-08-28T19:02:58.915Z"
  },
  "__v": 0
},
{
  "_id": {
    "$oid": "68b0a97f5955199db1d26477"
  },
  "message": "Yes, there will be class",
  "type": "success",
  "createdAt": {
    "$date": "2025-08-28T19:09:51.655Z"
  },
  "updatedAt": {
    "$date": "2025-08-28T19:09:51.655Z"
  },
  "__v": 0
},
{
  "_id": {
    "$oid": "68b0a9b25955199db1d2647b"
  },
  "message": "MADE BY ISRAEL Njor",
  "type": "success",
  "createdAt": {
    "$date": "2025-08-28T19:10:42.682Z"
  },
  "updatedAt": {
    "$date": "2025-08-28T19:10:42.682Z"
  },
  "__v": 0
}]